{"category": 0, "inputs": [{"type": "dataset-id", "description": "Dataset que se usara como fuente para la ejecucion", "name": "dataset"}, {"default": "leverage", "type": "string", "description": "Introducir un tipo de estrategia de busqueda: leverage, lift, support, lhs_cover, confidence", "name": "estrategia-busqueda"}, {"default": 20, "type": "number", "description": "Numero de anomalias a identificar", "name": "number-anomalies"}, {"default": 0, "type": "number", "description": "tipo de algoritmo para cluster 0 = g-means, 1 = k-meas", "name": "tipo-cluster"}, {"default": 5, "type": "number", "description": "valor critico en el caso de usar g-means, numero de clusters k en el caso de usar k-means", "name": "valor"}], "description": "Script para crear tomando como fuente un Dataset: Clusters, Anomalias y Asociaciones", "tags": [], "outputs": [{"type": "anomaly-id", "description": "Anomalias creadas con el recurso", "name": "anomaly"}, {"type": "association-id", "description": "Asociaciones creadas con el recurso", "name": "association"}, {"type": "cluster-id", "description": "Cluster creado con el recurso", "name": "cluster"}], "name": "Script-Dataset"}